btgsolutions_dataservices/__init__.py
btgsolutions_dataservices/config.py
btgsolutions_dataservices/exceptions.py
btgsolutions_dataservices/rest/__init__.py
btgsolutions_dataservices/rest/authenticator.py
btgsolutions_dataservices/rest/bulk_data.py
btgsolutions_dataservices/rest/company_data.py
btgsolutions_dataservices/rest/corporate_events.py
btgsolutions_dataservices/rest/hfn.py
btgsolutions_dataservices/rest/historical_candles.py
btgsolutions_dataservices/rest/intraday_candles.py
btgsolutions_dataservices/rest/intraday_tick_data.py
btgsolutions_dataservices/rest/public_sources.py
btgsolutions_dataservices/rest/quotes.py
btgsolutions_dataservices/rest/reference_data.py
btgsolutions_dataservices/rest/stock_loan.py
btgsolutions_dataservices/rest/ticker_last_event.py
btgsolutions_dataservices/websocket/__init__.py
btgsolutions_dataservices/websocket/hfn_websocket_client.py
btgsolutions_dataservices/websocket/market_data_feed.py
btgsolutions_dataservices/websocket/market_data_websocket_client.py
btgsolutions_dataservices/websocket/websocket_default_functions.py
btgsolutions_dataservices_python_client-2.16.0.dist-info/licenses/LICENSE
btgsolutions_dataservices_python_client-2.16.0.dist-info/METADATA
btgsolutions_dataservices_python_client-2.16.0.dist-info/WHEEL
btgsolutions_dataservices_python_client-2.16.0.dist-info/top_level.txt
btgsolutions_dataservices_python_client-2.16.0.dist-info/RECORD
