Metadata-Version: 2.4
Name: btgsolutions-dataservices-python-client
Version: 2.16.0
Summary: Python package containing several classes and data for extracting and manipulating market and trading data.
Home-page: https://github.com/BTG-Pactual-Solutions/btgsolutions-dataservices-python-client
Author: BTG Solutions Data Services powered by BTG Pactual Solutions
Requires-Python: >=3.9,<3.14
License-File: LICENSE
Requires-Dist: pandas>=2.2.2
Requires-Dist: websocket-client>=1.8.0
Requires-Dist: PyJWT>=2.8.0
Requires-Dist: requests>=2.32.3
Requires-Dist: pyarrow>=17.0.0
Dynamic: author
Dynamic: description
Dynamic: description-content-type
Dynamic: home-page
Dynamic: license-file
Dynamic: requires-dist
Dynamic: requires-python
Dynamic: summary
